{
  "project_info": {
    "project_number": "568492421002",
    "project_id": "wwf-api",
    "storage_bucket": "wwf-api.appspot.com"
  },
  "client": [
    {
      "client_info": {
        "mobilesdk_app_id": "1:568492421002:android:7c4403a5b9b498d64aa273",
        "android_client_info": {
          "package_name": "com.wwf.learning"
        }
      },
      "oauth_client": [
        {
          "client_id": "568492421002-9tmambg9uuk73he8s8m3ajbb41vlg7jq.apps.googleusercontent.com",
          "client_type": 3
        }
      ],
      "api_key": [
        {
          "current_key": "AIzaSyDj0U4rgeyCqhIBxhZ_2jhsPfFqw1CaiCU"
        }
      ],
      "services": {
        "appinvite_service": {
          "other_platform_oauth_client": [
            {
              "client_id": "568492421002-9tmambg9uuk73he8s8m3ajbb41vlg7jq.apps.googleusercontent.com",
              "client_type": 3
            },
            {
              "client_id": "568492421002-u6rd8fqvguuapmuk6k0a56q4nhrfidl6.apps.googleusercontent.com",
              "client_type": 2,
              "ios_info": {
                "bundle_id": "com.wwf.learning"
              }
            }
          ]
        }
      }
    },
    {
      "client_info": {
        "mobilesdk_app_id": "1:568492421002:android:05267fc9add6e5c94aa273",
        "android_client_info": {
          "package_name": "com.wwf.learning"
        }
      },
      "oauth_client": [
        {
          "client_id": "568492421002-9tmambg9uuk73he8s8m3ajbb41vlg7jq.apps.googleusercontent.com",
          "client_type": 3
        }
      ],
      "api_key": [
        {
          "current_key": "AIzaSyDj0U4rgeyCqhIBxhZ_2jhsPfFqw1CaiCU"
        }
      ],
      "services": {
        "appinvite_service": {
          "other_platform_oauth_client": [
            {
              "client_id": "568492421002-9tmambg9uuk73he8s8m3ajbb41vlg7jq.apps.googleusercontent.com",
              "client_type": 3
            },
            {
              "client_id": "568492421002-u6rd8fqvguuapmuk6k0a56q4nhrfidl6.apps.googleusercontent.com",
              "client_type": 2,
              "ios_info": {
                "bundle_id": "com.wwf.learning"
              }
            }
          ]
        }
      }
    }
  ],
  "configuration_version": "1"
}
